topsispack/__init__.py
topsispack/topsis.py
Topsis_Rishit_101903699-1.0.0.dist-info/LICENSE
Topsis_Rishit_101903699-1.0.0.dist-info/METADATA
Topsis_Rishit_101903699-1.0.0.dist-info/WHEEL
Topsis_Rishit_101903699-1.0.0.dist-info/top_level.txt
Topsis_Rishit_101903699-1.0.0.dist-info/RECORD
